{
  "variants": {
    "facing=east,half=lower,shape=inner": {
      "model": "xkdeco:block/blue_roof_small_eave_inner"
    },
    "facing=east,half=lower,shape=left_end": {
      "model": "xkdeco:block/blue_roof_small_eave_left_end"
    },
    "facing=east,half=lower,shape=outer": {
      "model": "xkdeco:block/blue_roof_small_eave_outer"
    },
    "facing=east,half=lower,shape=right_end": {
      "model": "xkdeco:block/blue_roof_small_eave_right_end"
    },
    "facing=east,half=lower,shape=straight": {
      "model": "xkdeco:block/blue_roof_small_eave"
    },
    "facing=east,half=upper,shape=inner": {
      "model": "xkdeco:block/blue_roof_small_eave_inner_top"
    },
    "facing=east,half=upper,shape=left_end": {
      "model": "xkdeco:block/blue_roof_small_eave_left_end_top"
    },
    "facing=east,half=upper,shape=outer": {
      "model": "xkdeco:block/blue_roof_small_eave_outer_top"
    },
    "facing=east,half=upper,shape=right_end": {
      "model": "xkdeco:block/blue_roof_small_eave_right_end_top"
    },
    "facing=east,half=upper,shape=straight": {
      "model": "xkdeco:block/blue_roof_small_eave_top"
    },
    "facing=north,half=lower,shape=inner": {
      "model": "xkdeco:block/blue_roof_small_eave_inner",
      "y": 270
    },
    "facing=north,half=lower,shape=left_end": {
      "model": "xkdeco:block/blue_roof_small_eave_left_end",
      "y": 270
    },
    "facing=north,half=lower,shape=outer": {
      "model": "xkdeco:block/blue_roof_small_eave_outer",
      "y": 270
    },
    "facing=north,half=lower,shape=right_end": {
      "model": "xkdeco:block/blue_roof_small_eave_right_end",
      "y": 270
    },
    "facing=north,half=lower,shape=straight": {
      "model": "xkdeco:block/blue_roof_small_eave",
      "y": 270
    },
    "facing=north,half=upper,shape=inner": {
      "model": "xkdeco:block/blue_roof_small_eave_inner_top",
      "y": 270
    },
    "facing=north,half=upper,shape=left_end": {
      "model": "xkdeco:block/blue_roof_small_eave_left_end_top",
      "y": 270
    },
    "facing=north,half=upper,shape=outer": {
      "model": "xkdeco:block/blue_roof_small_eave_outer_top",
      "y": 270
    },
    "facing=north,half=upper,shape=right_end": {
      "model": "xkdeco:block/blue_roof_small_eave_right_end_top",
      "y": 270
    },
    "facing=north,half=upper,shape=straight": {
      "model": "xkdeco:block/blue_roof_small_eave_top",
      "y": 270
    },
    "facing=south,half=lower,shape=inner": {
      "model": "xkdeco:block/blue_roof_small_eave_inner",
      "y": 90
    },
    "facing=south,half=lower,shape=left_end": {
      "model": "xkdeco:block/blue_roof_small_eave_left_end",
      "y": 90
    },
    "facing=south,half=lower,shape=outer": {
      "model": "xkdeco:block/blue_roof_small_eave_outer",
      "y": 90
    },
    "facing=south,half=lower,shape=right_end": {
      "model": "xkdeco:block/blue_roof_small_eave_right_end",
      "y": 90
    },
    "facing=south,half=lower,shape=straight": {
      "model": "xkdeco:block/blue_roof_small_eave",
      "y": 90
    },
    "facing=south,half=upper,shape=inner": {
      "model": "xkdeco:block/blue_roof_small_eave_inner_top",
      "y": 90
    },
    "facing=south,half=upper,shape=left_end": {
      "model": "xkdeco:block/blue_roof_small_eave_left_end_top",
      "y": 90
    },
    "facing=south,half=upper,shape=outer": {
      "model": "xkdeco:block/blue_roof_small_eave_outer_top",
      "y": 90
    },
    "facing=south,half=upper,shape=right_end": {
      "model": "xkdeco:block/blue_roof_small_eave_right_end_top",
      "y": 90
    },
    "facing=south,half=upper,shape=straight": {
      "model": "xkdeco:block/blue_roof_small_eave_top",
      "y": 90
    },
    "facing=west,half=lower,shape=inner": {
      "model": "xkdeco:block/blue_roof_small_eave_inner",
      "y": 180
    },
    "facing=west,half=lower,shape=left_end": {
      "model": "xkdeco:block/blue_roof_small_eave_left_end",
      "y": 180
    },
    "facing=west,half=lower,shape=outer": {
      "model": "xkdeco:block/blue_roof_small_eave_outer",
      "y": 180
    },
    "facing=west,half=lower,shape=right_end": {
      "model": "xkdeco:block/blue_roof_small_eave_right_end",
      "y": 180
    },
    "facing=west,half=lower,shape=straight": {
      "model": "xkdeco:block/blue_roof_small_eave",
      "y": 180
    },
    "facing=west,half=upper,shape=inner": {
      "model": "xkdeco:block/blue_roof_small_eave_inner_top",
      "y": 180
    },
    "facing=west,half=upper,shape=left_end": {
      "model": "xkdeco:block/blue_roof_small_eave_left_end_top",
      "y": 180
    },
    "facing=west,half=upper,shape=outer": {
      "model": "xkdeco:block/blue_roof_small_eave_outer_top",
      "y": 180
    },
    "facing=west,half=upper,shape=right_end": {
      "model": "xkdeco:block/blue_roof_small_eave_right_end_top",
      "y": 180
    },
    "facing=west,half=upper,shape=straight": {
      "model": "xkdeco:block/blue_roof_small_eave_top",
      "y": 180
    }
  }
}